{"6sJBZWuzI+qkqPToTZoBlw==":"dragon%201-121x121.jpg","QJ6wQ2/GGl/Hwnc/M2GOLA==":"deviant_dragons_featured_image_600x400-600x400.jpg","05kBG7jeEp2Vb0qDBmaslw==":"deviant_dragons_logo_image_350x350-350x350.jpg","vFegOM9A9TGPi+SgPp8APA==":"webp.net-gifmaker%20(1).gif","bC4GRYL8H885++54XsRQ3Q==":"nftcalendar-logo-190x190.png","npB26/CCpQWzQmfPFNuqQg==":"webp.net-gifmaker.gif","T/idmjJyJ264E7RS1pt6OQ==":"minnie%204-1076x1460.jpg","RDfvtj2dDleiiC8lkTFE1Q==":"minnie%205-1080x1440.jpg","T8lQXc2IjDpfYrVt0wv4tQ==":"minnie%205-1080x1440.jpeg","F2kr38cQLLFItRC68SQ25Q==":"minnie%20banner%20image-1025x463.jpg","oyAkeZ086S1UTuwnc1rM1w==":"minnie%2016-1064x1460.jpg","X/f3yXDz+kbaWHYZWxSKAA==":"webp.net-gifmaker-1.gif","M7yl1Pst2bJmAIy+j/kQeQ==":"minnie%209-121x176.jpg"}